{
  "info": {
    "key": "g2264_0217"
  },
  "sheets": {
    "מזומנים": {
      "columns": [
        "שם המנפיק/שם נייר ערך",
        "מספר ני\"ע",
        "מספר מנפיק",
        "דירוג",
        "שם מדרג",
        "סוג מטבע",
        "שיעור ריבית",
        "תשואה לפדיון",
        "שווי שוק",
        "שעור מנכסי אפיק ההשקעה"
      ],
      "data": [
        [
          "סכומים לקבל תנועות בזמן T",
          "",
          "",
          "AA+",
          "מעלות",
          "שקל חדש",
          0.0,
          0,
          6.08,
          6.07
        ],
        [
          "עו\"שים שונים",
          "",
          "",
          "AA+",
          "מעלות",
          "שקל חדש",
          0.0,
          0,
          0.09,
          0.09
        ],
        [
          "פועלים סהר - שקל חדש",
          "12 - 111111222",
          512199381,
          "AA+",
          "מעלות",
          "שקל חדש",
          0.02,
          0,
          94.02,
          93.84
        ]
      ]
    },
    "מניות": {
      "columns": [
        "שם המנפיק/שם נייר ערך",
        "מספר ני\"ע",
        "זירת מסחר",
        "ספק המידע",
        "מספר מנפיק",
        "ענף מסחר",
        "סוג מטבע",
        "ערך נקוב",
        "שער",
        "דיבידנד לקבל",
        "שווי שוק",
        "שעור מערך נקוב מונפק",
        "שעור מנכסי אפיק ההשקעה",
        "שעור מסך נכסי השקעה"
      ],
      "data": [
        [
          "אלביט מערכות",
          1081124,
          "TASE",
          "",
          520043027,
          "ביטחוניות",
          "שקל חדש",
          2786.0,
          43030.0,
          0.0,
          1198.82,
          0.01,
          3.96,
          3.95
        ],
        [
          "'אופקו הלת",
          1129543,
          "TASE",
          "",
          2279206,
          "השקעות במדעי החיים",
          "שקל חדש",
          48474.0,
          2346.0,
          0.0,
          1137.2,
          0.01,
          3.76,
          3.75
        ],
        [
          "טאואר סמיקונדקטור",
          1082379,
          "TASE",
          "",
          520041997,
          "מוליכים למחצה",
          "שקל חדש",
          10422.0,
          8416.0,
          0.0,
          877.12,
          0.01,
          2.9,
          2.89
        ],
        [
          "אורמת טכנו",
          1134402,
          "TASE",
          "",
          2250,
          "קלינטק",
          "שקל חדש",
          4318.9,
          20540.0,
          0.0,
          887.1,
          0.01,
          2.93,
          2.92
        ],
        [
          "נייס מערכות",
          273011,
          "TASE",
          "",
          520036872,
          "תוכנה ואינטרנט",
          "שקל חדש",
          6521.0,
          27980.0,
          0.0,
          1824.58,
          0.01,
          6.03,
          6.01
        ],
        [
          "בתי זיקוק לנפט (בזן)",
          2590248,
          "TASE",
          "",
          520036658,
          "אנרגיה",
          "שקל חדש",
          208321.0,
          153.6,
          0.0,
          319.98,
          0.01,
          1.06,
          1.05
        ],
        [
          "פז נפט",
          1100007,
          "TASE",
          "",
          510216054,
          "אנרגיה",
          "שקל חדש",
          1103.0,
          59610.0,
          0.0,
          657.5,
          0.01,
          2.17,
          2.17
        ],
        [
          "טבע",
          629014,
          "TASE",
          "",
          520013954,
          "פארמה",
          "שקל חדש",
          19197.0,
          11540.0,
          0.0,
          2215.33,
          0.0,
          7.32,
          7.3
        ],
        [
          "מיילן",
          1136704,
          "TASE",
          "",
          1655,
          "פארמה",
          "שקל חדש",
          15207.0,
          13590.0,
          0.0,
          2066.63,
          0.0,
          6.83,
          6.81
        ],
        [
          "פריגו",
          1130699,
          "TASE",
          "",
          529592,
          "פארמה",
          "שקל חדש",
          7928.0,
          26580.0,
          0.0,
          2107.26,
          0.01,
          6.96,
          6.94
        ],
        [
          "הבנק הבינלאומי",
          593038,
          "TASE",
          "",
          520029083,
          "בנקים",
          "שקל חדש",
          6537.0,
          6326.0,
          0.0,
          413.53,
          0.01,
          1.37,
          1.36
        ],
        [
          "דיסקונט",
          691212,
          "TASE",
          "",
          520007030,
          "בנקים",
          "שקל חדש",
          126401.0,
          919.9,
          0.0,
          1162.76,
          0.01,
          3.84,
          3.83
        ],
        [
          "לאומי",
          604611,
          "TASE",
          "",
          520018078,
          "בנקים",
          "שקל חדש",
          125818.0,
          1697.0,
          0.0,
          2135.13,
          0.01,
          7.06,
          7.03
        ],
        [
          "מזרחי טפחות",
          695437,
          "TASE",
          "",
          520000522,
          "בנקים",
          "שקל חדש",
          15135.0,
          6350.0,
          0.0,
          961.07,
          0.01,
          3.18,
          3.17
        ],
        [
          "הפועלים",
          662577,
          "TASE",
          "",
          520000118,
          "בנקים",
          "שקל חדש",
          92958.0,
          2354.0,
          0.0,
          2188.23,
          0.01,
          7.23,
          7.21
        ],
        [
          "הראל השקעות",
          585018,
          "TASE",
          "",
          520033986,
          "ביטוח",
          "שקל חדש",
          13958.0,
          2067.0,
          9.77,
          298.28,
          0.01,
          0.99,
          0.98
        ],
        [
          "בזק",
          230011,
          "TASE",
          "",
          520031931,
          "תקשורת ומדיה",
          "שקל חדש",
          240244.0,
          579.5,
          0.0,
          1392.21,
          0.01,
          4.6,
          4.59
        ],
        [
          "סלקום",
          1101534,
          "TASE",
          "",
          511930125,
          "תקשורת ומדיה",
          "שקל חדש",
          6555.0,
          3361.0,
          0.0,
          220.31,
          0.01,
          0.73,
          0.73
        ],
        [
          "פרטנר",
          1083484,
          "TASE",
          "",
          520044314,
          "תקשורת ומדיה",
          "שקל חדש",
          13832.0,
          1853.0,
          0.0,
          256.31,
          0.01,
          0.85,
          0.84
        ],
        [
          "איירפורט סיטי",
          1095835,
          "TASE",
          "",
          511659401,
          "נדל\"ן ובינוי",
          "שקל חדש",
          7498.0,
          4830.0,
          0.0,
          362.15,
          0.01,
          1.2,
          1.19
        ],
        [
          "אלוני-חץ",
          390013,
          "TASE",
          "",
          520038506,
          "נדל\"ן ובינוי",
          "שקל חדש",
          14301.0,
          3529.0,
          0.0,
          504.68,
          0.01,
          1.67,
          1.66
        ],
        [
          "אמות",
          1097278,
          "TASE",
          "",
          520026683,
          "נדל\"ן ובינוי",
          "שקל חדש",
          15190.0,
          1830.0,
          0.0,
          277.98,
          0.0,
          0.92,
          0.92
        ],
        [
          "ביג",
          1097260,
          "TASE",
          "",
          513623314,
          "נדל\"ן ובינוי",
          "שקל חדש",
          518.0,
          24800.0,
          0.0,
          128.46,
          0.0,
          0.42,
          0.42
        ],
        [
          "גזית גלוב",
          126011,
          "TASE",
          "",
          520033234,
          "נדל\"ן ובינוי",
          "שקל חדש",
          12741.0,
          3372.0,
          4.52,
          434.15,
          0.01,
          1.43,
          1.43
        ],
        [
          "מליסרון מ\"ר 1 ש\"ח",
          323014,
          "TASE",
          "",
          520037789,
          "נדל\"ן ובינוי",
          "שקל חדש",
          2173.0,
          18350.0,
          0.0,
          398.75,
          0.0,
          1.32,
          1.31
        ],
        [
          "עזריאלי קבוצה",
          1119478,
          "TASE",
          "",
          510960719,
          "נדל\"ן ובינוי",
          "שקל חדש",
          4610.0,
          19400.0,
          0.0,
          894.34,
          0.0,
          2.96,
          2.95
        ],
        [
          "סודהסטרים",
          1121300,
          "TASE",
          "",
          513951251,
          "מזון",
          "שקל חדש",
          2365.0,
          18690.0,
          0.0,
          442.02,
          0.01,
          1.46,
          1.46
        ],
        [
          "פרוטרום תעשיות בע\"מ מ\"ר",
          1081082,
          "TASE",
          "",
          520042805,
          "מזון",
          "שקל חדש",
          5154.0,
          24410.0,
          0.0,
          1258.09,
          0.01,
          4.16,
          4.14
        ],
        [
          "שטראוס",
          746016,
          "TASE",
          "",
          520003781,
          "מזון",
          "שקל חדש",
          5447.0,
          6833.0,
          0.0,
          372.19,
          0.0,
          1.23,
          1.23
        ],
        [
          "כימיקלים לישראל",
          281014,
          "TASE",
          "",
          520027830,
          "כימיה גומי ופלסטיק",
          "שקל חדש",
          62372.0,
          1647.0,
          0.0,
          1027.27,
          0.0,
          3.39,
          3.38
        ],
        [
          "קבוצת דלק בע\"מ מ\"ר 1",
          1084128,
          "TASE",
          "",
          520044322,
          "השקעה ואחזקות",
          "שקל חדש",
          456.0,
          76310.0,
          0.0,
          347.97,
          0.0,
          1.15,
          1.15
        ],
        [
          "חברה לישראל",
          576017,
          "TASE",
          "",
          520028010,
          "השקעה ואחזקות",
          "שקל חדש",
          502.0,
          74200.0,
          0.0,
          372.48,
          0.01,
          1.23,
          1.23
        ],
        [
          "דלק ניהול קידוחים יה\"ש",
          475020,
          "TASE",
          "",
          550013098,
          "חיפושי נפט וגז",
          "שקל חדש",
          38007.0,
          1383.0,
          0.0,
          525.64,
          0.0,
          1.74,
          1.73
        ],
        [
          "ישראמקו יהש",
          232017,
          "TASE",
          "",
          550010003,
          "חיפושי נפט וגז",
          "שקל חדש",
          1125193.0,
          52.5,
          0.0,
          590.73,
          0.01,
          1.95,
          1.95
        ],
        [
          "ארפורט זכויות 3",
          1141043,
          "TASE",
          "",
          511659401,
          "נדל\"ן ובינוי",
          "שקל חדש",
          0.73,
          1231.0,
          0.0,
          0.01,
          0.0,
          0.0,
          0.0
        ]
      ]
    }
  }
}